[
  {
    "Group": "1",
    "Credits": "3",
    "Name": "اصول مهندسی و علم مواد",
    "Prereqs": "",
    "Capacity": "35",
    "EnrolledStudents": "",
    "Professor": "عباس اکبرزاده چنگیز",
    "ExamDate": "",
    "ClassTime": "شنبه 15:0 تا 18:0",
    "Comments": "توجه:این کد درس مختص دانشجویان رشته مهندسی صنایع و مواد و متالورژی\n              می باشد.",
    "MessageOnSignup": "",
    "CourseID": "57012"
  },
  {
    "Group": "1",
    "Credits": "3",
    "Name": "علم مواد",
    "Prereqs": "",
    "Capacity": "35",
    "EnrolledStudents": "",
    "Professor": "عباس اکبرزاده چنگیز",
    "ExamDate": "",
    "ClassTime": "شنبه 15:0 تا 18:0",
    "Comments": "توجه: این کد درس مختص دانشجویان رشته مهندسی عمران می باشد.",
    "MessageOnSignup": "",
    "CourseID": "57021"
  }
]
