[
  {
    "Group": "1",
    "Credits": "3",
    "Name": "آمار و احتمال مهندسی",
    "Prereqs": "پیش‌نیاز: 22015",
    "Capacity": "50",
    "EnrolledStudents": "50",
    "Professor": "هاتف عبدوس",
    "ExamDate": "1402/11/04   09:00",
    "ClassTime": "شنبه و دوشنبه از 13:30 تا 15:0",
    "Comments": "",
    "MessageOnSignup": "مخصوص دانشجویان مهندسی عمران",
    "CourseID": "مخصوص دانشجویان مهندسی عمران"
  },
  {
    "Group": "2",
    "Credits": "3",
    "Name": "محاسبات عددی",
    "Prereqs": "پیش‌نیاز: 40153",
    "Capacity": "30",
    "EnrolledStudents": "29",
    "Professor": "حامد خرازی",
    "ExamDate": "1402/11/03   09:00",
    "ClassTime": "یکشنبه و سه شنبه از 15:0 تا 16:30",
    "Comments": "",
    "MessageOnSignup": "",
    "CourseID": ""
  },
  {
    "Group": "1",
    "Credits": "3",
    "Name": "محاسبات عددی",
    "Prereqs": "پیش‌نیاز: 40153",
    "Capacity": "30",
    "EnrolledStudents": "30",
    "Professor": "سعید سعید منیر",
    "ExamDate": "1402/11/03   09:00",
    "ClassTime": "یکشنبه و سه شنبه از 13:30 تا 15:0",
    "Comments": "",
    "MessageOnSignup": "",
    "CourseID": ""
  },
  {
    "Group": "1",
    "Credits": "0",
    "Name": "آشنایی با مهندسی عمران",
    "Prereqs": "",
    "Capacity": "12",
    "EnrolledStudents": "12",
    "Professor": "علی رضا معززی مهر طهران",
    "ExamDate": "",
    "ClassTime": "چهارشنبه از 15:0 تا 17:0",
    "Comments": "",
    "MessageOnSignup": "مخصوص ورودی جدید",
    "CourseID": "مخصوص ورودی جدید"
  },
  {
    "Group": "1",
    "Credits": "3",
    "Name": "قابلیت اعتماد، ریسک و تاب‌آوری",
    "Prereqs": "پیش‌نیاز: 20005",
    "Capacity": "35",
    "EnrolledStudents": "35",
    "Professor": "مجتبی محصولی",
    "ExamDate": "1402/11/02   09:00",
    "ClassTime": "شنبه و دوشنبه از 9:0 تا 10:30",
    "Comments": "",
    "MessageOnSignup": "دانشجویان پردیس نمی توانند در این درس ثبت نام کنند",
    "CourseID": "دانشجویان پردیس نمی توانند در این درس ثبت نام کنند"
  },
  {
    "Group": "1",
    "Credits": "3",
    "Name": "استاتیک",
    "Prereqs": "همنیاز: 22015",
    "Capacity": "30",
    "EnrolledStudents": "11",
    "Professor": "مجتبی طباطبائیان نیم آورد",
    "ExamDate": "1402/10/23   09:00",
    "ClassTime": "یکشنبه و سه شنبه از 15:0 تا 16:30",
    "Comments": "",
    "MessageOnSignup": "",
    "CourseID": ""
  },
  {
    "Group": "1",
    "Credits": "3",
    "Name": "دینامیک",
    "Prereqs": "پیش‌نیاز: 20011",
    "Capacity": "45",
    "EnrolledStudents": "42",
    "Professor": "علی بخشی",
    "ExamDate": "1402/11/01   09:00",
    "ClassTime": "یکشنبه و سه شنبه از 10:30 تا 12:0",
    "Comments": "",
    "MessageOnSignup": "",
    "CourseID": ""
  },
  {
    "Group": "2",
    "Credits": "3",
    "Name": "دینامیک",
    "Prereqs": "پیش‌نیاز: 20011",
    "Capacity": "45",
    "EnrolledStudents": "45",
    "Professor": "شقایق واثقی امیری",
    "ExamDate": "1402/11/01   09:00",
    "ClassTime": "یکشنبه و سه شنبه از 10:30 تا 12:0",
    "Comments": "",
    "MessageOnSignup": "",
    "CourseID": ""
  },
  {
    "Group": "1",
    "Credits": "2",
    "Name": "طراحی سازه‌های بتنی ۲",
    "Prereqs": "پیش‌نیاز: 20231",
    "Capacity": "33",
    "EnrolledStudents": "33",
    "Professor": "مجتبی طباطبائیان نیم آورد",
    "ExamDate": "1402/11/03   15:00",
    "ClassTime": "یکشنبه از 13:0 تا 15:0",
    "Comments": "",
    "MessageOnSignup": "",
    "CourseID": ""
  },
  {
    "Group": "1",
    "Credits": "3",
    "Name": "بارگذاری سازه‌ها",
    "Prereqs": "پیش‌نیاز: 20121",
    "Capacity": "38",
    "EnrolledStudents": "37",
    "Professor": "علی رضا معززی مهر طهران",
    "ExamDate": "1402/11/01   09:00",
    "ClassTime": "یکشنبه و سه شنبه از 10:30 تا 12:0",
    "Comments": "",
    "MessageOnSignup": "",
    "CourseID": ""
  },
  {
    "Group": "1",
    "Credits": "1",
    "Name": "آز جامدات",
    "Prereqs": "پیش‌نیاز: 20111",
    "Capacity": "15",
    "EnrolledStudents": "4",
    "Professor": "علیرضا خالو",
    "ExamDate": "",
    "ClassTime": "یکشنبه از 13:0 تا 15:0",
    "Comments": "",
    "MessageOnSignup": "",
    "CourseID": ""
  },
  {
    "Group": "2",
    "Credits": "1",
    "Name": "آز جامدات",
    "Prereqs": "پیش‌نیاز: 20111",
    "Capacity": "15",
    "EnrolledStudents": "15",
    "Professor": "وهب توفیق",
    "ExamDate": "",
    "ClassTime": "دوشنبه از 7:0 تا 9:0",
    "Comments": "",
    "MessageOnSignup": "",
    "CourseID": ""
  },
  {
    "Group": "2",
    "Credits": "3",
    "Name": "مکانیک جامدات ۱",
    "Prereqs": "پیش‌نیاز: 20011",
    "Capacity": "40",
    "EnrolledStudents": "40",
    "Professor": "حسین محمدی شجاع",
    "ExamDate": "1402/10/27   09:00",
    "ClassTime": "شنبه و دوشنبه از 9:0 تا 10:30",
    "Comments": "",
    "MessageOnSignup": "",
    "CourseID": ""
  },
  {
    "Group": "1",
    "Credits": "3",
    "Name": "مکانیک جامدات ۱",
    "Prereqs": "پیش‌نیاز: 20011",
    "Capacity": "40",
    "EnrolledStudents": "40",
    "Professor": "امیررضا خوئی",
    "ExamDate": "1402/10/27   09:00",
    "ClassTime": "شنبه و دوشنبه از 9:0 تا 10:30",
    "Comments": "",
    "MessageOnSignup": "",
    "CourseID": ""
  },
  {
    "Group": "1",
    "Credits": "3",
    "Name": "مهندسی راه و ترافیک",
    "Prereqs": "پیش‌نیاز: 20513 و 20411",
    "Capacity": "33",
    "EnrolledStudents": "33",
    "Professor": "سینا صاحبی",
    "ExamDate": "1402/10/24   15:00",
    "ClassTime": "شنبه و دوشنبه از 9:0 تا 10:30",
    "Comments": "",
    "MessageOnSignup": "",
    "CourseID": ""
  },
  {
    "Group": "1",
    "Credits": "3",
    "Name": "تئوری سازه ۱",
    "Prereqs": "پیش‌نیاز: 20111 همنیاز: 20012",
    "Capacity": "30",
    "EnrolledStudents": "13",
    "Professor": "هاتف عبدوس",
    "ExamDate": "1402/10/30   09:00",
    "ClassTime": "شنبه و دوشنبه از 15:0 تا 16:30",
    "Comments": "",
    "MessageOnSignup": "",
    "CourseID": ""
  },
  {
    "Group": "1",
    "Credits": "3",
    "Name": "تئوری سازه ۲",
    "Prereqs": "پیش‌نیاز: 20121",
    "Capacity": "20",
    "EnrolledStudents": "",
    "Professor": "پیمان رحمت آبادی",
    "ExamDate": "1402/11/04   15:00",
    "ClassTime": "یکشنبه و سه شنبه از 15:0 تا 16:30",
    "Comments": "",
    "MessageOnSignup": "",
    "CourseID": ""
  },
  {
    "Group": "1",
    "Credits": "3",
    "Name": "مبانی مهندسی زلزله",
    "Prereqs": "پیش‌نیاز: 20121",
    "Capacity": "35",
    "EnrolledStudents": "8",
    "Professor": "محمدتقی کاظمی",
    "ExamDate": "1402/11/02   09:00",
    "ClassTime": "شنبه و دوشنبه از 9:0 تا 10:30",
    "Comments": "",
    "MessageOnSignup": "",
    "CourseID": ""
  },
  {
    "Group": "1",
    "Credits": "3",
    "Name": "مصالح‌ساختمانی‌ و تکنولوژی‌ بتن‌ و آز",
    "Prereqs": "پیش‌نیاز: 20111",
    "Capacity": "30",
    "EnrolledStudents": "23",
    "Professor": "وهب توفیق",
    "ExamDate": "1402/10/23   09:00",
    "ClassTime": "شنبه از 7:0 تا 9:0 و شنبه از 13:0 تا 15:0",
    "Comments": "",
    "MessageOnSignup": "آز : شنبه 15-13",
    "CourseID": "آز : شنبه 15-13"
  },
  {
    "Group": "1",
    "Credits": "3",
    "Name": "طرح سازه‌های فولادی ۱",
    "Prereqs": "پیش‌نیاز: 20121",
    "Capacity": "38",
    "EnrolledStudents": "37",
    "Professor": "شروین ملکی",
    "ExamDate": "1402/11/01   09:00",
    "ClassTime": "یکشنبه و سه شنبه از 10:30 تا 12:0",
    "Comments": "",
    "MessageOnSignup": "",
    "CourseID": ""
  },
  {
    "Group": "2",
    "Credits": "3",
    "Name": "طرح سازه‌های فولادی ۱",
    "Prereqs": "پیش‌نیاز: 20121",
    "Capacity": "41",
    "EnrolledStudents": "41",
    "Professor": "همایون اسمعیل پوراستکانچی",
    "ExamDate": "1402/11/01   09:00",
    "ClassTime": "یکشنبه و سه شنبه از 10:30 تا 12:0",
    "Comments": "",
    "MessageOnSignup": "",
    "CourseID": ""
  },
  {
    "Group": "1",
    "Credits": "2",
    "Name": "طرح سازه‌های فولادی ۲",
    "Prereqs": "پیش‌نیاز: 20221",
    "Capacity": "38",
    "EnrolledStudents": "38",
    "Professor": "محمدعلی فیوضات",
    "ExamDate": "1402/10/26   09:00",
    "ClassTime": "سه شنبه از 13:0 تا 15:0",
    "Comments": "",
    "MessageOnSignup": "",
    "CourseID": ""
  },
  {
    "Group": "1",
    "Credits": "3",
    "Name": "طرح سازه‌های بتنی ۱",
    "Prereqs": "پیش‌نیاز: 20121 همنیاز: 20208",
    "Capacity": "36",
    "EnrolledStudents": "36",
    "Professor": "علیرضا خالو",
    "ExamDate": "1402/10/25   15:00",
    "ClassTime": "شنبه و دوشنبه از 10:30 تا 12:0",
    "Comments": "",
    "MessageOnSignup": "",
    "CourseID": ""
  },
  {
    "Group": "2",
    "Credits": "3",
    "Name": "طرح سازه‌های بتنی ۱",
    "Prereqs": "پیش‌نیاز: 20121 همنیاز: 20208",
    "Capacity": "40",
    "EnrolledStudents": "40",
    "Professor": "کیارش محتشم دولتشاهی",
    "ExamDate": "1402/10/25   15:00",
    "ClassTime": "شنبه و دوشنبه از 10:30 تا 12:0",
    "Comments": "",
    "MessageOnSignup": "",
    "CourseID": ""
  },
  {
    "Group": "1",
    "Credits": "1",
    "Name": "پروژه‌ سازه‌های ‌فولادی",
    "Prereqs": "پیش‌نیاز: 20224",
    "Capacity": "35",
    "EnrolledStudents": "4",
    "Professor": "پنام زرفام",
    "ExamDate": "",
    "ClassTime": "یکشنبه از 15:0 تا 16:30",
    "Comments": "",
    "MessageOnSignup": "",
    "CourseID": ""
  },
  {
    "Group": "1",
    "Credits": "1",
    "Name": "پروژه سازه‌های بتنی",
    "Prereqs": "پیش‌نیاز: 20017",
    "Capacity": "20",
    "EnrolledStudents": "",
    "Professor": "پنام زرفام",
    "ExamDate": "",
    "ClassTime": "یکشنبه از 16:30 تا 18:0",
    "Comments": "",
    "MessageOnSignup": "",
    "CourseID": ""
  },
  {
    "Group": "1",
    "Credits": "3",
    "Name": "مدیریت پروژه و ساخت",
    "Prereqs": "پیش‌نیاز: 20311",
    "Capacity": "35",
    "EnrolledStudents": "35",
    "Professor": "حامد حاج کاظم کاشانی",
    "ExamDate": "1402/10/25   15:00",
    "ClassTime": "شنبه و دوشنبه از 10:30 تا 12:0",
    "Comments": "",
    "MessageOnSignup": "",
    "CourseID": ""
  },
  {
    "Group": "2",
    "Credits": "3",
    "Name": "مدیریت پروژه و ساخت",
    "Prereqs": "پیش‌نیاز: 20311",
    "Capacity": "32",
    "EnrolledStudents": "29",
    "Professor": "امین الوانچی",
    "ExamDate": "1402/10/25   15:00",
    "ClassTime": "شنبه و دوشنبه از 10:30 تا 12:0",
    "Comments": "",
    "MessageOnSignup": "",
    "CourseID": ""
  },
  {
    "Group": "1",
    "Credits": "3",
    "Name": "روش‌های‌ ساخت و ماشین‌های‌ راهسازی",
    "Prereqs": "پیش‌نیاز: 20411",
    "Capacity": "35",
    "EnrolledStudents": "35",
    "Professor": "رضا عندلیب",
    "ExamDate": "1402/11/02   09:00",
    "ClassTime": "شنبه و دوشنبه از 9:0 تا 10:30",
    "Comments": "",
    "MessageOnSignup": "دانشجویان پردیس نمی توانند در این درس ثبت نام کنند",
    "CourseID": "دانشجویان پردیس نمی توانند در این درس ثبت نام کنند"
  },
  {
    "Group": "2",
    "Credits": "3",
    "Name": "روش‌های‌ ساخت و ماشین‌های‌ راهسازی",
    "Prereqs": "پیش‌نیاز: 20411",
    "Capacity": "30",
    "EnrolledStudents": "25",
    "Professor": "امیرحسین سنگکی",
    "ExamDate": "1402/11/02   09:00",
    "ClassTime": "یکشنبه و سه شنبه از 16:30 تا 18:0",
    "Comments": "",
    "MessageOnSignup": "",
    "CourseID": ""
  },
  {
    "Group": "2",
    "Credits": "2",
    "Name": "طراحی معماری",
    "Prereqs": "پیش‌نیاز: 35201",
    "Capacity": "33",
    "EnrolledStudents": "33",
    "Professor": "فرشته بیگلی",
    "ExamDate": "1402/10/24   09:00",
    "ClassTime": "چهارشنبه از 13:0 تا 16:0",
    "Comments": "",
    "MessageOnSignup": "تمرین طراحی معماری:چهارشنبه16-15",
    "CourseID": "تمرین طراحی معماری:چهارشنبه16-15"
  },
  {
    "Group": "1",
    "Credits": "2",
    "Name": "طراحی معماری",
    "Prereqs": "پیش‌نیاز: 35201",
    "Capacity": "33",
    "EnrolledStudents": "33",
    "Professor": "فرشته بیگلی",
    "ExamDate": "1402/10/24   09:00",
    "ClassTime": "چهارشنبه از 8:0 تا 11:0",
    "Comments": "",
    "MessageOnSignup": "تمرین طراحی معماری: چهارشنبه 11-10",
    "CourseID": "تمرین طراحی معماری: چهارشنبه 11-10"
  },
  {
    "Group": "4",
    "Credits": "1",
    "Name": "آز مکانیک خاک",
    "Prereqs": "پیش‌نیاز: 20411",
    "Capacity": "18",
    "EnrolledStudents": "18",
    "Professor": "حامد صادقی",
    "ExamDate": "",
    "ClassTime": "شنبه از 13:0 تا 15:0",
    "Comments": "",
    "MessageOnSignup": "",
    "CourseID": ""
  },
  {
    "Group": "1",
    "Credits": "1",
    "Name": "آز مکانیک خاک",
    "Prereqs": "پیش‌نیاز: 20411",
    "Capacity": "18",
    "EnrolledStudents": "18",
    "Professor": "حامد صادقی",
    "ExamDate": "",
    "ClassTime": "دوشنبه از 13:0 تا 15:0",
    "Comments": "",
    "MessageOnSignup": "",
    "CourseID": ""
  },
  {
    "Group": "2",
    "Credits": "1",
    "Name": "آز مکانیک خاک",
    "Prereqs": "پیش‌نیاز: 20411",
    "Capacity": "15",
    "EnrolledStudents": "15",
    "Professor": "محمدمهدی احمدی",
    "ExamDate": "",
    "ClassTime": "چهارشنبه از 13:0 تا 15:0",
    "Comments": "",
    "MessageOnSignup": "",
    "CourseID": ""
  },
  {
    "Group": "5",
    "Credits": "1",
    "Name": "آز مکانیک خاک",
    "Prereqs": "پیش‌نیاز: 20411",
    "Capacity": "18",
    "EnrolledStudents": "18",
    "Professor": "حامد صادقی",
    "ExamDate": "",
    "ClassTime": "چهارشنبه از 8:0 تا 10:0",
    "Comments": "",
    "MessageOnSignup": "",
    "CourseID": ""
  },
  {
    "Group": "3",
    "Credits": "1",
    "Name": "آز مکانیک خاک",
    "Prereqs": "پیش‌نیاز: 20411",
    "Capacity": "12",
    "EnrolledStudents": "10",
    "Professor": "محمدمهدی احمدی",
    "ExamDate": "",
    "ClassTime": "چهارشنبه از 10:0 تا 12:0",
    "Comments": "",
    "MessageOnSignup": "",
    "CourseID": ""
  },
  {
    "Group": "1",
    "Credits": "3",
    "Name": "مکانیک خاک",
    "Prereqs": "پیش‌نیاز: 20111 و 20451 همنیاز: 20615",
    "Capacity": "30",
    "EnrolledStudents": "22",
    "Professor": "سیدمحسن حائری",
    "ExamDate": "1402/11/02   09:00",
    "ClassTime": "شنبه و دوشنبه از 9:0 تا 10:30",
    "Comments": "",
    "MessageOnSignup": "",
    "CourseID": ""
  },
  {
    "Group": "1",
    "Credits": "3",
    "Name": "مهندسی پی",
    "Prereqs": "پیش‌نیاز: 20411 و 20401 همنیاز: 20231",
    "Capacity": "30",
    "EnrolledStudents": "25",
    "Professor": "حامد صادقی",
    "ExamDate": "1402/11/02   09:00",
    "ClassTime": "شنبه و دوشنبه از 7:30 تا 9:0",
    "Comments": "",
    "MessageOnSignup": "",
    "CourseID": ""
  },
  {
    "Group": "2",
    "Credits": "3",
    "Name": "روسازی راه و آز",
    "Prereqs": "پیش‌نیاز: 20411",
    "Capacity": "22",
    "EnrolledStudents": "22",
    "Professor": "محمدرضا صبوری",
    "ExamDate": "1402/11/03   09:00",
    "ClassTime": "یکشنبه و سه شنبه از 13:30 تا 15:0 و چهارشنبه از 10:30 تا 12:30",
    "Comments": "",
    "MessageOnSignup": "آز: چهارشنبه 12:30-10:30",
    "CourseID": "آز: چهارشنبه 12:30-10:30"
  },
  {
    "Group": "3",
    "Credits": "3",
    "Name": "روسازی راه و آز",
    "Prereqs": "پیش‌نیاز: 20411",
    "Capacity": "23",
    "EnrolledStudents": "23",
    "Professor": "نادر طباطبائی",
    "ExamDate": "1402/11/03   09:00",
    "ClassTime": "یکشنبه و سه شنبه از 13:30 تا 15:0 و چهارشنبه از 10:30 تا 12:30",
    "Comments": "",
    "MessageOnSignup": "",
    "CourseID": ""
  },
  {
    "Group": "1",
    "Credits": "3",
    "Name": "روسازی راه و آز",
    "Prereqs": "پیش‌نیاز: 20411",
    "Capacity": "22",
    "EnrolledStudents": "22",
    "Professor": "محمدرضا صبوری",
    "ExamDate": "1402/11/03   09:00",
    "ClassTime": "شنبه از 13:0 تا 15:0 و یکشنبه و سه شنبه از 13:30 تا 15:0",
    "Comments": "",
    "MessageOnSignup": "آز: شنبه 15-13",
    "CourseID": "آز: شنبه 15-13"
  },
  {
    "Group": "1",
    "Credits": "2",
    "Name": "زمین‌شناسی",
    "Prereqs": "همنیاز: 20111",
    "Capacity": "40",
    "EnrolledStudents": "37",
    "Professor": "مهرداد بانی خیر",
    "ExamDate": "1402/10/25   15:00",
    "ClassTime": "دوشنبه از 13:0 تا 15:0",
    "Comments": "",
    "MessageOnSignup": "",
    "CourseID": ""
  },
  {
    "Group": "2",
    "Credits": "2",
    "Name": "زمین‌شناسی",
    "Prereqs": "همنیاز: 20111",
    "Capacity": "41",
    "EnrolledStudents": "41",
    "Professor": "مهرداد بانی خیر",
    "ExamDate": "1402/10/25   15:00",
    "ClassTime": "دوشنبه از 15:0 تا 17:0",
    "Comments": "",
    "MessageOnSignup": "",
    "CourseID": ""
  },
  {
    "Group": "1",
    "Credits": "1",
    "Name": "آز هیدرولیک",
    "Prereqs": "همنیاز: 20611",
    "Capacity": "18",
    "EnrolledStudents": "17",
    "Professor": "بهزاد عطائی آشتیانی",
    "ExamDate": "",
    "ClassTime": "چهارشنبه از 8:0 تا 10:0",
    "Comments": "",
    "MessageOnSignup": "",
    "CourseID": ""
  },
  {
    "Group": "2",
    "Credits": "1",
    "Name": "آز هیدرولیک",
    "Prereqs": "همنیاز: 20611",
    "Capacity": "18",
    "EnrolledStudents": "16",
    "Professor": "بهزاد عطائی آشتیانی",
    "ExamDate": "",
    "ClassTime": "چهارشنبه از 13:0 تا 15:0",
    "Comments": "",
    "MessageOnSignup": "",
    "CourseID": ""
  },
  {
    "Group": "1",
    "Credits": "3",
    "Name": "هیدرولیک",
    "Prereqs": "پیش‌نیاز: 20615",
    "Capacity": "38",
    "EnrolledStudents": "38",
    "Professor": "محمد راعی",
    "ExamDate": "1402/10/24   15:00",
    "ClassTime": "یکشنبه و سه شنبه از 9:0 تا 10:30",
    "Comments": "",
    "MessageOnSignup": "",
    "CourseID": ""
  },
  {
    "Group": "2",
    "Credits": "3",
    "Name": "هیدرولیک",
    "Prereqs": "پیش‌نیاز: 20615",
    "Capacity": "35",
    "EnrolledStudents": "34",
    "Professor": "سید رضی شیخ الاسلامی",
    "ExamDate": "1402/10/24   15:00",
    "ClassTime": "یکشنبه و سه شنبه از 9:0 تا 10:30",
    "Comments": "",
    "MessageOnSignup": "",
    "CourseID": ""
  },
  {
    "Group": "1",
    "Credits": "3",
    "Name": "مکانیک سیالات",
    "Prereqs": "پیش‌نیاز: 20012 همنیاز: 20111",
    "Capacity": "30",
    "EnrolledStudents": "19",
    "Professor": "فرخنده خراشادی زاده",
    "ExamDate": "1402/10/24   15:00",
    "ClassTime": "یکشنبه و سه شنبه از 9:0 تا 10:30",
    "Comments": "",
    "MessageOnSignup": "",
    "CourseID": ""
  },
  {
    "Group": "1",
    "Credits": "3",
    "Name": "مهندسی آب و فاضلاب",
    "Prereqs": "پیش‌نیاز: 20611 همنیاز: 20669",
    "Capacity": "35",
    "EnrolledStudents": "35",
    "Professor": "عمار صفائی نعمت اللهی",
    "ExamDate": "1402/11/01   09:00",
    "ClassTime": "یکشنبه و سه شنبه از 10:30 تا 12:0",
    "Comments": "",
    "MessageOnSignup": "",
    "CourseID": ""
  },
  {
    "Group": "1",
    "Credits": "2",
    "Name": "هیدرولوژی مهندسی",
    "Prereqs": "پیش‌نیاز: 20005 همنیاز: 20615",
    "Capacity": "30",
    "EnrolledStudents": "23",
    "Professor": "ساناز مقیم",
    "ExamDate": "1402/10/26   09:00",
    "ClassTime": "یکشنبه از 7:0 تا 9:0",
    "Comments": "",
    "MessageOnSignup": "",
    "CourseID": ""
  },
  {
    "Group": "1",
    "Credits": "3",
    "Name": "مهندسی محیط زیست",
    "Prereqs": "پیش‌نیاز: 23011 و 20629",
    "Capacity": "30",
    "EnrolledStudents": "11",
    "Professor": "محمد دانش یزدی",
    "ExamDate": "1402/11/01   09:00",
    "ClassTime": "یکشنبه و سه شنبه از 10:30 تا 12:0",
    "Comments": "",
    "MessageOnSignup": "",
    "CourseID": ""
  },
  {
    "Group": "1",
    "Credits": "0",
    "Name": "کارآموزی",
    "Prereqs": "",
    "Capacity": "",
    "EnrolledStudents": "3",
    "Professor": "وهب توفیق",
    "ExamDate": "",
    "ClassTime": "",
    "Comments": "",
    "MessageOnSignup": "مطابق قوانین کارآموزی دانشکده و دانشگاه",
    "CourseID": "مطابق قوانین کارآموزی دانشکده و دانشگاه"
  },
  {
    "Group": "1",
    "Credits": "0",
    "Name": "پروژه کارشناسی",
    "Prereqs": "",
    "Capacity": "20",
    "EnrolledStudents": "12",
    "Professor": "عمار صفائی نعمت اللهی",
    "ExamDate": "",
    "ClassTime": "",
    "Comments": "",
    "MessageOnSignup": "شرایط اخذ درس مطابق با قوانین مندرج در سایت دانشکده",
    "CourseID": "شرایط اخذ درس مطابق با قوانین مندرج در سایت دانشکده"
  },
  {
    "Group": "1",
    "Credits": "3",
    "Name": "مطالعه خاص",
    "Prereqs": "",
    "Capacity": "25",
    "EnrolledStudents": "25",
    "Professor": "محمدمهدی احمدی",
    "ExamDate": "1402/10/30   09:00",
    "ClassTime": "شنبه و دوشنبه از 15:0 تا 16:30",
    "Comments": "",
    "MessageOnSignup": "عنوان درس :آموخته های خرابی در پروژه های مهندسی عمران.\n              پیشنیاز:دروس فولاد 1، بتن1 و مهندسی پی. برای اخذ درس گرفتن تایید\n              مدرس درس لازم است.",
    "CourseID": "عنوان :درس آموخته های خرابی در پروژه های مهندسی عمران.\n              پیشنیاز:دروس فولاد 1، بتن1 و مهندسی پی. برای اخذ درس گرفتن تایید\n              مدرس درس لازم است."
  },
  {
    "Group": "1",
    "Credits": "3",
    "Name": "مطالعه خاص",
    "Prereqs": "",
    "Capacity": "36",
    "EnrolledStudents": "35",
    "Professor": "سید رضی شیخ الاسلامی",
    "ExamDate": "1402/11/03   09:00",
    "ClassTime": "یکشنبه و سه شنبه از 13:30 تا 15:0",
    "Comments": "",
    "MessageOnSignup": "عنوان درس: آشنایی با طراحی بناهای آبی درس پیشنیاز:هیدرولیک",
    "CourseID": "عنوان درس: آشنایی با طراحی بناهای آبی درس پیشنیاز:هیدرولیک"
  },
  {
    "Group": "1",
    "Credits": "3",
    "Name": "مطالعه خاص",
    "Prereqs": "",
    "Capacity": "38",
    "EnrolledStudents": "38",
    "Professor": "محمدمسعود آقامحمدحسین تجریشی",
    "ExamDate": "1402/10/30   15:00",
    "ClassTime": "یکشنبه و سه شنبه از 15:0 تا 16:30",
    "Comments": "",
    "MessageOnSignup": "عنوان درس: برنامه ریزی در مهندسی عمران ذرس همنیاز: مدیریت پروژه و\n              ساخت",
    "CourseID": "عنوان درس: برنامه ریزی در مهندسی عمران ذرس همنیاز: مدیریت پروژه و\n              ساخت"
  },
  {
    "Group": "1",
    "Credits": "3",
    "Name": "رفتار شکل‌پذیر سازه‌های فولادی",
    "Prereqs": "",
    "Capacity": "20",
    "EnrolledStudents": "1",
    "Professor": "سیدوحید خونساری",
    "ExamDate": "1402/10/30   09:00",
    "ClassTime": "شنبه و دوشنبه از 15:0 تا 16:30",
    "Comments": "",
    "MessageOnSignup": "",
    "CourseID": ""
  },
  {
    "Group": "1",
    "Credits": "3",
    "Name": "ریاضی مهندسی پیشرفته",
    "Prereqs": "",
    "Capacity": "30",
    "EnrolledStudents": "24",
    "Professor": "ساناز مقیم",
    "ExamDate": "1402/10/24   15:00",
    "ClassTime": "یکشنبه و سه شنبه از 9:0 تا 10:30",
    "Comments": "",
    "MessageOnSignup": "مخصوص گرایش آب و محیط زیست",
    "CourseID": "مخصوص گرایش آب و محیط زیست"
  },
  {
    "Group": "4",
    "Credits": "3",
    "Name": "ریاضی مهندسی پیشرفته",
    "Prereqs": "",
    "Capacity": "20",
    "EnrolledStudents": "13",
    "Professor": "کیارش محتشم دولتشاهی",
    "ExamDate": "1402/10/27   09:00",
    "ClassTime": "شنبه و دوشنبه از 7:30 تا 9:0",
    "Comments": "",
    "MessageOnSignup": "",
    "CourseID": ""
  },
  {
    "Group": "3",
    "Credits": "3",
    "Name": "ریاضی مهندسی پیشرفته",
    "Prereqs": "",
    "Capacity": "26",
    "EnrolledStudents": "26",
    "Professor": "فیاض رحیم زاده روفوئی",
    "ExamDate": "1402/11/01   09:00",
    "ClassTime": "یکشنبه و سه شنبه از 10:30 تا 12:0",
    "Comments": "",
    "MessageOnSignup": "",
    "CourseID": ""
  },
  {
    "Group": "2",
    "Credits": "3",
    "Name": "ریاضی مهندسی پیشرفته",
    "Prereqs": "",
    "Capacity": "20",
    "EnrolledStudents": "20",
    "Professor": "محمدعلی فیوضات",
    "ExamDate": "1402/11/01   09:00",
    "ClassTime": "یکشنبه و سه شنبه از 10:30 تا 12:0",
    "Comments": "",
    "MessageOnSignup": "",
    "CourseID": ""
  },
  {
    "Group": "1",
    "Credits": "3",
    "Name": "ترمیم و بهسازی سازه‌ها به وسیله الیاف پلیمری",
    "Prereqs": "پیش‌نیاز: 20017",
    "Capacity": "20",
    "EnrolledStudents": "7",
    "Professor": "وهب توفیق",
    "ExamDate": "1402/10/23   09:00",
    "ClassTime": "شنبه و دوشنبه از 9:0 تا 10:30",
    "Comments": "",
    "MessageOnSignup": "",
    "CourseID": ""
  },
  {
    "Group": "1",
    "Credits": "3",
    "Name": "قابلیت اعتماد سازه و مدل‌سازی احتمالاتی",
    "Prereqs": "",
    "Capacity": "20",
    "EnrolledStudents": "20",
    "Professor": "مجتبی محصولی",
    "ExamDate": "1402/10/25   15:00",
    "ClassTime": "شنبه و دوشنبه از 10:30 تا 12:0",
    "Comments": "",
    "MessageOnSignup": "",
    "CourseID": ""
  },
  {
    "Group": "1",
    "Credits": "3",
    "Name": "تئوری الاستیسیته ۱",
    "Prereqs": "",
    "Capacity": "30",
    "EnrolledStudents": "25",
    "Professor": "حسین محمدی شجاع",
    "ExamDate": "1402/11/04   09:00",
    "ClassTime": "شنبه و دوشنبه از 13:30 تا 15:0",
    "Comments": "",
    "MessageOnSignup": "",
    "CourseID": ""
  },
  {
    "Group": "1",
    "Credits": "3",
    "Name": "روش زمان دوام",
    "Prereqs": "",
    "Capacity": "21",
    "EnrolledStudents": "21",
    "Professor": "همایون اسمعیل پوراستکانچی",
    "ExamDate": "1402/10/24   15:00",
    "ClassTime": "یکشنبه و سه شنبه از 9:0 تا 10:30",
    "Comments": "",
    "MessageOnSignup": "",
    "CourseID": ""
  },
  {
    "Group": "1",
    "Credits": "3",
    "Name": "روش‌های عددی آنالیز سازه‌ها",
    "Prereqs": "",
    "Capacity": "5",
    "EnrolledStudents": "5",
    "Professor": "مسعود مفید",
    "ExamDate": "1402/10/30   09:00",
    "ClassTime": "شنبه و دوشنبه از 15:0 تا 16:30",
    "Comments": "",
    "MessageOnSignup": "فقط دانشجویان دکترای سازه و زلزله در این درس میتوانند ثبت نام\n              کنند.تایید مدرس درس لازم است",
    "CourseID": "فقط دانشجویان دکترای سازه و زلزله در این درس میتوانند ثبت نام\n              کنند.تایید مدرس درس لازم است"
  },
  {
    "Group": "1",
    "Credits": "3",
    "Name": "عناصر محدود",
    "Prereqs": "",
    "Capacity": "20",
    "EnrolledStudents": "12",
    "Professor": "امیررضا خوئی",
    "ExamDate": "1402/10/25   15:00",
    "ClassTime": "شنبه و دوشنبه از 10:30 تا 12:0",
    "Comments": "",
    "MessageOnSignup": "",
    "CourseID": ""
  },
  {
    "Group": "1",
    "Credits": "3",
    "Name": "ارتعاشات سازه‌ها",
    "Prereqs": "",
    "Capacity": "30",
    "EnrolledStudents": "30",
    "Professor": "علی رضا معززی مهر طهران",
    "ExamDate": "1402/10/23   09:00",
    "ClassTime": "یکشنبه و سه شنبه از 15:0 تا 16:30",
    "Comments": "",
    "MessageOnSignup": "",
    "CourseID": ""
  },
  {
    "Group": "2",
    "Credits": "3",
    "Name": "ارتعاشات سازه‌ها",
    "Prereqs": "",
    "Capacity": "30",
    "EnrolledStudents": "",
    "Professor": "حسن علیجانی مقدم",
    "ExamDate": "1402/10/23   09:00",
    "ClassTime": "شنبه و دوشنبه از 10:30 تا 12:0",
    "Comments": "",
    "MessageOnSignup": "",
    "CourseID": ""
  },
  {
    "Group": "1",
    "Credits": "3",
    "Name": "ارتعاشات تصادفی",
    "Prereqs": "همنیاز: 20153",
    "Capacity": "20",
    "EnrolledStudents": "4",
    "Professor": "علی بخشی",
    "ExamDate": "1402/11/03   09:00",
    "ClassTime": "یکشنبه و سه شنبه از 13:30 تا 15:0",
    "Comments": "",
    "MessageOnSignup": "",
    "CourseID": ""
  },
  {
    "Group": "1",
    "Credits": "3",
    "Name": "مهندسی زلزله پیشرفته",
    "Prereqs": "",
    "Capacity": "30",
    "EnrolledStudents": "27",
    "Professor": "فیاض رحیم زاده روفوئی",
    "ExamDate": "1402/10/24   15:00",
    "ClassTime": "یکشنبه و سه شنبه از 9:0 تا 10:30",
    "Comments": "",
    "MessageOnSignup": "",
    "CourseID": ""
  },
  {
    "Group": "1",
    "Credits": "3",
    "Name": "تکنولوژی عالی بتن",
    "Prereqs": "",
    "Capacity": "22",
    "EnrolledStudents": "22",
    "Professor": "علیرضا خالو",
    "ExamDate": "1402/11/02   09:00",
    "ClassTime": "شنبه و دوشنبه از 9:0 تا 10:30",
    "Comments": "",
    "MessageOnSignup": "",
    "CourseID": ""
  },
  {
    "Group": "1",
    "Credits": "3",
    "Name": "طراحی پل‌های فولادی",
    "Prereqs": "",
    "Capacity": "22",
    "EnrolledStudents": "22",
    "Professor": "شروین ملکی",
    "ExamDate": "1402/10/19   09:00",
    "ClassTime": "یکشنبه و سه شنبه از 13:0 تا 14:30",
    "Comments": "",
    "MessageOnSignup": "",
    "CourseID": ""
  },
  {
    "Group": "1",
    "Credits": "3",
    "Name": "طراحی سازه‌های آبی",
    "Prereqs": "",
    "Capacity": "30",
    "EnrolledStudents": "7",
    "Professor": "ابوالفضل شمسائی",
    "ExamDate": "1402/10/25   15:00",
    "ClassTime": "شنبه و دوشنبه از 10:30 تا 12:0",
    "Comments": "",
    "MessageOnSignup": "",
    "CourseID": ""
  },
  {
    "Group": "1",
    "Credits": "1",
    "Name": "سمینار مهندسی و مدیریت ساخت",
    "Prereqs": "",
    "Capacity": "30",
    "EnrolledStudents": "6",
    "Professor": "حامد حاج کاظم کاشانی",
    "ExamDate": "",
    "ClassTime": "دوشنبه از 15:0 تا 16:30",
    "Comments": "",
    "MessageOnSignup": "",
    "CourseID": ""
  },
  {
    "Group": "1",
    "Credits": "3",
    "Name": "روش‌های برنامه‌ریزی و کنترل پروژه",
    "Prereqs": "",
    "Capacity": "30",
    "EnrolledStudents": "7",
    "Professor": "امین الوانچی",
    "ExamDate": "1402/10/27   09:00",
    "ClassTime": "شنبه و دوشنبه از 7:30 تا 9:0",
    "Comments": "",
    "MessageOnSignup": "",
    "CourseID": ""
  },
  {
    "Group": "1",
    "Credits": "4",
    "Name": "تحقیق در عملیات",
    "Prereqs": "",
    "Capacity": "30",
    "EnrolledStudents": "13",
    "Professor": "یوسف شفاهی",
    "ExamDate": "1402/10/25   15:00",
    "ClassTime": "شنبه و دوشنبه از 10:30 تا 12:30",
    "Comments": "",
    "MessageOnSignup": "",
    "CourseID": ""
  },
  {
    "Group": "1",
    "Credits": "3",
    "Name": "مکانیک خاکهای غیر اشباع",
    "Prereqs": "پیش‌نیاز: 20401 و 20411 همنیاز: 20410",
    "Capacity": "20",
    "EnrolledStudents": "12",
    "Professor": "حامد صادقی",
    "ExamDate": "1402/10/25   15:00",
    "ClassTime": "شنبه و دوشنبه از 10:30 تا 12:0",
    "Comments": "",
    "MessageOnSignup": "",
    "CourseID": ""
  },
  {
    "Group": "1",
    "Credits": "3",
    "Name": "روش‌های‌ عددی ‌پیشرفته‌ در ژئومکانیک",
    "Prereqs": "",
    "Capacity": "20",
    "EnrolledStudents": "10",
    "Professor": "علی پاک",
    "ExamDate": "1402/11/02   09:00",
    "ClassTime": "شنبه و دوشنبه از 9:0 تا 10:30",
    "Comments": "",
    "MessageOnSignup": "",
    "CourseID": ""
  },
  {
    "Group": "1",
    "Credits": "3",
    "Name": "مکانیک خاک پیشرفته ۱",
    "Prereqs": "",
    "Capacity": "30",
    "EnrolledStudents": "18",
    "Professor": "فردین جعفرزاده",
    "ExamDate": "1402/10/30   09:00",
    "ClassTime": "شنبه و دوشنبه از 15:0 تا 16:30",
    "Comments": "",
    "MessageOnSignup": "",
    "CourseID": ""
  },
  {
    "Group": "1",
    "Credits": "3",
    "Name": "پی پیشرفته",
    "Prereqs": "",
    "Capacity": "30",
    "EnrolledStudents": "15",
    "Professor": "محمدمهدی احمدی",
    "ExamDate": "1402/11/04   09:00",
    "ClassTime": "شنبه و دوشنبه از 13:30 تا 15:0",
    "Comments": "",
    "MessageOnSignup": "",
    "CourseID": ""
  },
  {
    "Group": "1",
    "Credits": "3",
    "Name": "ژئوتکنیک لرزه‌ای",
    "Prereqs": "",
    "Capacity": "20",
    "EnrolledStudents": "7",
    "Professor": "فردین جعفرزاده",
    "ExamDate": "1402/11/04   09:00",
    "ClassTime": "شنبه و دوشنبه از 13:30 تا 15:0",
    "Comments": "",
    "MessageOnSignup": "",
    "CourseID": ""
  },
  {
    "Group": "1",
    "Credits": "3",
    "Name": "دینامیک خاک",
    "Prereqs": "",
    "Capacity": "30",
    "EnrolledStudents": "13",
    "Professor": "سیدمحسن حائری",
    "ExamDate": "1402/10/25   15:00",
    "ClassTime": "شنبه و دوشنبه از 10:30 تا 12:0",
    "Comments": "",
    "MessageOnSignup": "",
    "CourseID": ""
  },
  {
    "Group": "1",
    "Credits": "3",
    "Name": "مکانیک سنگ",
    "Prereqs": "",
    "Capacity": "30",
    "EnrolledStudents": "11",
    "Professor": "محمدحسین صدقیانی",
    "ExamDate": "1402/10/27   09:00",
    "ClassTime": "شنبه و دوشنبه از 7:30 تا 9:0",
    "Comments": "",
    "MessageOnSignup": "",
    "CourseID": ""
  },
  {
    "Group": "1",
    "Credits": "3",
    "Name": "طراحی روسازی راه پیشرفته",
    "Prereqs": "پیش‌نیاز: 20436",
    "Capacity": "30",
    "EnrolledStudents": "4",
    "Professor": "نادر طباطبائی",
    "ExamDate": "1402/10/24   15:00",
    "ClassTime": "یکشنبه و سه شنبه از 9:0 تا 10:30",
    "Comments": "",
    "MessageOnSignup": "",
    "CourseID": ""
  },
  {
    "Group": "1",
    "Credits": "3",
    "Name": "حمل و نقل هوشمند",
    "Prereqs": "",
    "Capacity": "20",
    "EnrolledStudents": "15",
    "Professor": "زهرا امینی",
    "ExamDate": "1402/11/04   09:00",
    "ClassTime": "شنبه و دوشنبه از 13:30 تا 15:0",
    "Comments": "",
    "MessageOnSignup": "",
    "CourseID": ""
  },
  {
    "Group": "1",
    "Credits": "3",
    "Name": "مهندسی ترافیک پیشرفته",
    "Prereqs": "",
    "Capacity": "30",
    "EnrolledStudents": "14",
    "Professor": "زهرا امینی",
    "ExamDate": "1402/11/01   09:00",
    "ClassTime": "شنبه و دوشنبه از 15:0 تا 16:30",
    "Comments": "",
    "MessageOnSignup": "",
    "CourseID": ""
  },
  {
    "Group": "1",
    "Credits": "3",
    "Name": "شبیه‌سازی",
    "Prereqs": "",
    "Capacity": "30",
    "EnrolledStudents": "11",
    "Professor": "امین الوانچی",
    "ExamDate": "1402/11/02   09:00",
    "ClassTime": "شنبه و دوشنبه از 9:0 تا 10:30",
    "Comments": "",
    "MessageOnSignup": "",
    "CourseID": ""
  },
  {
    "Group": "1",
    "Credits": "3",
    "Name": "برنامه‌ریزی حمل‌ونقل",
    "Prereqs": "",
    "Capacity": "30",
    "EnrolledStudents": "20",
    "Professor": "یوسف شفاهی",
    "ExamDate": "1402/11/02   09:00",
    "ClassTime": "شنبه و دوشنبه از 9:0 تا 10:30",
    "Comments": "",
    "MessageOnSignup": "",
    "CourseID": ""
  },
  {
    "Group": "1",
    "Credits": "3",
    "Name": "مبانی فرآیندها در مهندسی محیط زیست",
    "Prereqs": "",
    "Capacity": "30",
    "EnrolledStudents": "14",
    "Professor": "عمار صفائی نعمت اللهی",
    "ExamDate": "1402/11/03   09:00",
    "ClassTime": "یکشنبه و سه شنبه از 13:30 تا 15:0",
    "Comments": "",
    "MessageOnSignup": "",
    "CourseID": ""
  },
  {
    "Group": "1",
    "Credits": "3",
    "Name": "کاربرد RSوGISدر مهندسی عمران و آزمایشگاه",
    "Prereqs": "پیش‌نیاز: 40151 و 20669",
    "Capacity": "25",
    "EnrolledStudents": "25",
    "Professor": "محمد دانش یزدی",
    "ExamDate": "1402/11/04   09:00",
    "ClassTime": "یکشنبه و سه شنبه از 15:0 تا 16:30",
    "Comments": "",
    "MessageOnSignup": "",
    "CourseID": ""
  },
  {
    "Group": "1",
    "Credits": "3",
    "Name": "هیدرولوژی پیشرفته",
    "Prereqs": "",
    "Capacity": "30",
    "EnrolledStudents": "21",
    "Professor": "فرخنده خراشادی زاده",
    "ExamDate": "1402/10/26   09:00",
    "ClassTime": "یکشنبه و سه شنبه از 7:30 تا 9:0",
    "Comments": "",
    "MessageOnSignup": "",
    "CourseID": ""
  },
  {
    "Group": "1",
    "Credits": "3",
    "Name": "آلودگی مواد زائد جامد",
    "Prereqs": "",
    "Capacity": "20",
    "EnrolledStudents": "2",
    "Professor": "محمدمسعود آقامحمدحسین تجریشی",
    "ExamDate": "1402/10/23   09:00",
    "ClassTime": "یکشنبه و سه شنبه از 16:30 تا 18:0",
    "Comments": "",
    "MessageOnSignup": "",
    "CourseID": ""
  },
  {
    "Group": "1",
    "Credits": "3",
    "Name": "آنالیز و طرح سدهای بتنی",
    "Prereqs": "",
    "Capacity": "20",
    "EnrolledStudents": "6",
    "Professor": "محسن قائمیان",
    "ExamDate": "1402/10/24   15:00",
    "ClassTime": "یکشنبه و سه شنبه از 9:0 تا 10:30",
    "Comments": "",
    "MessageOnSignup": "",
    "CourseID": ""
  },
  {
    "Group": "1",
    "Credits": "3",
    "Name": "هیدرولیک پیشرفته",
    "Prereqs": "",
    "Capacity": "30",
    "EnrolledStudents": "23",
    "Professor": "محمد راعی",
    "ExamDate": "1402/11/01   09:00",
    "ClassTime": "یکشنبه و سه شنبه از 10:30 تا 12:0",
    "Comments": "",
    "MessageOnSignup": "",
    "CourseID": ""
  },
  {
    "Group": "1",
    "Credits": "3",
    "Name": "هیدرودینامیک محیط زیستی",
    "Prereqs": "",
    "Capacity": "30",
    "EnrolledStudents": "16",
    "Professor": "میرمصدق جمالی",
    "ExamDate": "1402/11/01   09:00",
    "ClassTime": "یکشنبه و سه شنبه از 10:30 تا 12:0",
    "Comments": "",
    "MessageOnSignup": "",
    "CourseID": ""
  },
  {
    "Group": "1",
    "Credits": "3",
    "Name": "مطالعه انفرادی",
    "Prereqs": "",
    "Capacity": "",
    "EnrolledStudents": "6",
    "Professor": "یوسف شفاهی",
    "ExamDate": "",
    "ClassTime": "",
    "Comments": "",
    "MessageOnSignup": "",
    "CourseID": ""
  },
  {
    "Group": "1",
    "Credits": "3",
    "Name": "عنوان خاص",
    "Prereqs": "",
    "Capacity": "20",
    "EnrolledStudents": "12",
    "Professor": "امیرحسن کرمانشاه",
    "ExamDate": "1402/10/25   15:00",
    "ClassTime": "شنبه و دوشنبه از 10:30 تا 12:0",
    "Comments": "",
    "MessageOnSignup": "عنوان درس: حمل و نقل پایدار",
    "CourseID": "عنوان درس: حمل و نقل پایدار"
  },
  {
    "Group": "1",
    "Credits": "0",
    "Name": "پایان‌نامه کارشناسی‌ارشد",
    "Prereqs": "",
    "Capacity": "",
    "EnrolledStudents": "94",
    "Professor": "یوسف شفاهی",
    "ExamDate": "",
    "ClassTime": "",
    "Comments": "",
    "MessageOnSignup": "",
    "CourseID": ""
  },
  {
    "Group": "1",
    "Credits": "1",
    "Name": "سمینار آب و سازه‌های آبی",
    "Prereqs": "",
    "Capacity": "30",
    "EnrolledStudents": "27",
    "Professor": "سید رضی شیخ الاسلامی",
    "ExamDate": "",
    "ClassTime": "یکشنبه از 12:0 تا 13:30",
    "Comments": "",
    "MessageOnSignup": "",
    "CourseID": ""
  },
  {
    "Group": "1",
    "Credits": "1",
    "Name": "سمینار سازه",
    "Prereqs": "",
    "Capacity": "30",
    "EnrolledStudents": "26",
    "Professor": "محمدعلی فیوضات",
    "ExamDate": "",
    "ClassTime": "یکشنبه از 12:0 تا 13:0",
    "Comments": "",
    "MessageOnSignup": "",
    "CourseID": ""
  },
  {
    "Group": "1",
    "Credits": "1",
    "Name": "سمینار خاک و پی",
    "Prereqs": "",
    "Capacity": "30",
    "EnrolledStudents": "12",
    "Professor": "محمدمهدی احمدی",
    "ExamDate": "",
    "ClassTime": "دوشنبه از 16:30 تا 18:0",
    "Comments": "",
    "MessageOnSignup": "",
    "CourseID": ""
  },
  {
    "Group": "1",
    "Credits": "1",
    "Name": "سمینار زلزله",
    "Prereqs": "",
    "Capacity": "30",
    "EnrolledStudents": "12",
    "Professor": "محسن قائمیان",
    "ExamDate": "",
    "ClassTime": "یکشنبه از 7:30 تا 9:0",
    "Comments": "",
    "MessageOnSignup": "",
    "CourseID": ""
  },
  {
    "Group": "1",
    "Credits": "1",
    "Name": "سمینار حمل‌ونقل",
    "Prereqs": "",
    "Capacity": "30",
    "EnrolledStudents": "11",
    "Professor": "امیرحسن کرمانشاه",
    "ExamDate": "",
    "ClassTime": "دوشنبه از 13:30 تا 15:0",
    "Comments": "",
    "MessageOnSignup": "",
    "CourseID": ""
  },
  {
    "Group": "1",
    "Credits": "1",
    "Name": "سمینار راه و ترابری",
    "Prereqs": "",
    "Capacity": "30",
    "EnrolledStudents": "5",
    "Professor": "محمدرضا صبوری",
    "ExamDate": "",
    "ClassTime": "یکشنبه از 15:0 تا 16:30",
    "Comments": "",
    "MessageOnSignup": "",
    "CourseID": ""
  },
  {
    "Group": "1",
    "Credits": "1",
    "Name": "سمینار ۲",
    "Prereqs": "",
    "Capacity": "30",
    "EnrolledStudents": "8",
    "Professor": "حامد حاج کاظم کاشانی",
    "ExamDate": "",
    "ClassTime": "",
    "Comments": "",
    "MessageOnSignup": "مخصوص گرایش مدیریت ساخت",
    "CourseID": "مخصوص گرایش مدیریت ساخت"
  },
  {
    "Group": "2",
    "Credits": "1",
    "Name": "سمینار ۲",
    "Prereqs": "",
    "Capacity": "30",
    "EnrolledStudents": "18",
    "Professor": "محمدرضا صبوری",
    "ExamDate": "",
    "ClassTime": "",
    "Comments": "",
    "MessageOnSignup": "مخصوص گرایش حمل و نقل و راه و ترابری",
    "CourseID": "مخصوص گرایش حمل و نقل و راه و ترابری"
  },
  {
    "Group": "1",
    "Credits": "3",
    "Name": "عنوان خاص",
    "Prereqs": "",
    "Capacity": "20",
    "EnrolledStudents": "19",
    "Professor": "حامد حاج کاظم کاشانی",
    "ExamDate": "1402/11/04   09:00",
    "ClassTime": "شنبه و دوشنبه از 13:30 تا 15:0",
    "Comments": "",
    "MessageOnSignup": "عنوان درس: برنامه ریزی برای ارتقاءتاب آوری زیرساخت ها. شرط اخذ\n              درس: تایید مدرس",
    "CourseID": "عنوان درس: برنامه ریزی برای ارتقاءتاب آوری زیرساخت ها. شرط اخذ\n              درس: تایید مدرس"
  },
  {
    "Group": "1",
    "Credits": "3",
    "Name": "سازه‌های نگهبان",
    "Prereqs": "پیش‌نیاز: 20413",
    "Capacity": "35",
    "EnrolledStudents": "12",
    "Professor": "علی پاک",
    "ExamDate": "1402/10/25   15:00",
    "ClassTime": "شنبه و دوشنبه از 10:30 تا 12:0",
    "Comments": "",
    "MessageOnSignup": "",
    "CourseID": ""
  },
  {
    "Group": "1",
    "Credits": "0",
    "Name": "امتحان جامع دکتری",
    "Prereqs": "",
    "Capacity": "",
    "EnrolledStudents": "10",
    "Professor": "یوسف شفاهی",
    "ExamDate": "",
    "ClassTime": "",
    "Comments": "",
    "MessageOnSignup": "",
    "CourseID": ""
  },
  {
    "Group": "1",
    "Credits": "0",
    "Name": "پیشنهاد پژوهشی",
    "Prereqs": "",
    "Capacity": "",
    "EnrolledStudents": "5",
    "Professor": "یوسف شفاهی",
    "ExamDate": "",
    "ClassTime": "",
    "Comments": "",
    "MessageOnSignup": "",
    "CourseID": ""
  },
  {
    "Group": "1",
    "Credits": "0",
    "Name": "رساله دکتری",
    "Prereqs": "",
    "Capacity": "",
    "EnrolledStudents": "17",
    "Professor": "یوسف شفاهی",
    "ExamDate": "",
    "ClassTime": "",
    "Comments": "",
    "MessageOnSignup": "",
    "CourseID": ""
  },
  {
    "Group": "1",
    "Credits": "0",
    "Name": "دفاع از رساله دکتری",
    "Prereqs": "",
    "Capacity": "",
    "EnrolledStudents": "",
    "Professor": "یوسف شفاهی",
    "ExamDate": "",
    "ClassTime": "",
    "Comments": "",
    "MessageOnSignup": "",
    "CourseID": ""
  },
  {
    "Group": "1",
    "Credits": "3",
    "Name": "دستیار آموزشی",
    "Prereqs": "",
    "Capacity": "",
    "EnrolledStudents": "26",
    "Professor": "یوسف شفاهی",
    "ExamDate": "",
    "ClassTime": "",
    "Comments": "",
    "MessageOnSignup": "",
    "CourseID": ""
  }
]
