[
  {
    "Group": "1",
    "Credits": "3",
    "Name": "درآمدی بر فلسفه",
    "Prereqs": "",
    "Capacity": "60",
    "EnrolledStudents": "47",
    "Professor": "ابراهیم آزادگان",
    "ExamDate": "",
    "ClassTime": "چهارشنبه از 10:0 تا 13:0",
    "Comments": "",
    "MessageOnSignup": "«از دروس الزامی دوره فرعی فلسفه علم»، ویژه دانشجویان دوره فرعی -\n              کلیه دانشجویان دانشگاهحداکثر ظرفیت برای ورودی های 1402 مقطع\n              کارشناسی ارشد دانشکده گروه فلسفه علم 0 می باشد.",
    "CourseID": ""
  },
  {
    "Group": "1",
    "Credits": "3",
    "Name": "درآمدی بر فیزیک",
    "Prereqs": "",
    "Capacity": "20",
    "EnrolledStudents": "8",
    "Professor": "مرتضی خطیری یانه سری",
    "ExamDate": "",
    "ClassTime": "شنبه از 9:0 تا 12:0",
    "Comments": "",
    "MessageOnSignup": "درس جبرانی (اجباری در ترم اول دانشجو) برای دانشجویان ارشد ورودی\n              1402گروه که کارشناسی آنها در علوم انسانی است - کلیه دانشجویان\n              دانشگاه",
    "CourseID": ""
  },
  {
    "Group": "1",
    "Credits": "3",
    "Name": "متافیزیک",
    "Prereqs": "",
    "Capacity": "20",
    "EnrolledStudents": "20",
    "Professor": "سید علی طاهری خرم آبادی",
    "ExamDate": "",
    "ClassTime": "سه شنبه از 13:30 تا 16:30",
    "Comments": "",
    "MessageOnSignup": "درس جبرانی (اجباری در ترم اول دانشجو) برای دانشجویان ارشد ورودی\n              1402 گروه که کارشناسی آنها در رشته های علوم پایه، فنی و یا مهندسی\n              است - دانشجویان دوره فرعی «فلسفه علم»، کلیه دانشجویان دانشگاه",
    "CourseID": ""
  },
  {
    "Group": "1",
    "Credits": "3",
    "Name": "فلسفه اسلامی ۱",
    "Prereqs": "",
    "Capacity": "25",
    "EnrolledStudents": "22",
    "Professor": "سیدحسن حسینی سروری",
    "ExamDate": "",
    "ClassTime": "یکشنبه از 9:0 تا 12:0",
    "Comments": "",
    "MessageOnSignup": "«از دروس الزامی دوره ارشد»، ویژه دانشجویان ارشد ورودی 1402 گروه",
    "CourseID": ""
  },
  {
    "Group": "1",
    "Credits": "3",
    "Name": "فلسفه علم ۱",
    "Prereqs": "",
    "Capacity": "23",
    "EnrolledStudents": "23",
    "Professor": "جواد اکبری تختمشلو",
    "ExamDate": "",
    "ClassTime": "یکشنبه از 13:30 تا 16:30",
    "Comments": "",
    "MessageOnSignup": "«از دروس الزامی دورۀ ارشد»، ویژه دانشجویان ارشد ورودی 1402 گروه\n              (اجباری در ترم اول دانشجو)",
    "CourseID": ""
  },
  {
    "Group": "1",
    "Credits": "3",
    "Name": "مقولات ویژه در فلسفه علم",
    "Prereqs": "",
    "Capacity": "20",
    "EnrolledStudents": "20",
    "Professor": "جواد اکبری تختمشلو",
    "ExamDate": "",
    "ClassTime": "سه شنبه از 13:30 تا 16:30",
    "Comments": "",
    "MessageOnSignup": "«از دروس اختیاری دورۀ ارشد» - کلیه دانشجویان گروه و دانشگاهحداکثر\n              ظرفیت برای ورودی های 1402 مقطع کارشناسی ارشد دانشکده گروه فلسفه\n              علم 0 می باشد.",
    "CourseID": ""
  },
  {
    "Group": "1",
    "Credits": "3",
    "Name": "ابعاد اجتماعی فضای رایانه‌ای",
    "Prereqs": "",
    "Capacity": "20",
    "EnrolledStudents": "12",
    "Professor": "ابراهیم آزادگان",
    "ExamDate": "",
    "ClassTime": "دوشنبه از 14:0 تا 17:0",
    "Comments": "",
    "MessageOnSignup": "«از دروس اختیاری دورۀ ارشد» - کلیه دانشجویان گروه و دانشگاهحداکثر\n              ظرفیت برای ورودی های 1402 مقطع دکتری دانشکده گروه فلسفه علم 0 می\n              باشد.\n              \n              حداکثر ظرفیت برای ورودی های 1402 مقطع کارشناسی ارشد دانشکده گروه\n              فلسفه علم 0 می باشد.",
    "CourseID": ""
  },
  {
    "Group": "1",
    "Credits": "3",
    "Name": "فلسفه علوم اجتماعی",
    "Prereqs": "",
    "Capacity": "20",
    "EnrolledStudents": "12",
    "Professor": "حمید پارسانیا",
    "ExamDate": "",
    "ClassTime": "سه شنبه از 9:0 تا 12:0",
    "Comments": "",
    "MessageOnSignup": "«از دروس اختیاری دورۀ ارشد» - کلیه دانشجویان گروه و دانشگاهحداکثر\n              ظرفیت برای ورودی های 1402 مقطع کارشناسی ارشد دانشکده گروه فلسفه\n              علم 0 می باشد.\n              \n              حداکثر ظرفیت برای مقطع کارشناسی 0 می باشد.",
    "CourseID": ""
  },
  {
    "Group": "1",
    "Credits": "3",
    "Name": "مبانی فلسفی مکانیک کوانتمی",
    "Prereqs": "",
    "Capacity": "20",
    "EnrolledStudents": "11",
    "Professor": "مرتضی خطیری یانه سری",
    "ExamDate": "",
    "ClassTime": "یکشنبه از 12:0 تا 15:0",
    "Comments": "",
    "MessageOnSignup": "«از دروس اختیاری دورۀ ارشد» - کلیه دانشجویان گروه و دانشگاهحداکثر\n              ظرفیت برای ورودی های 1402 مقطع کارشناسی ارشد دانشکده گروه فلسفه\n              علم 0 می باشد.\n              \n              حداکثر ظرفیت برای ورودی های 1402 مقطع دکتری دانشکده گروه فلسفه علم\n              0 می باشد.",
    "CourseID": ""
  },
  {
    "Group": "1",
    "Credits": "3",
    "Name": "مبانی منطق",
    "Prereqs": "",
    "Capacity": "30",
    "EnrolledStudents": "28",
    "Professor": "سعید انواری",
    "ExamDate": "",
    "ClassTime": "شنبه از 14:0 تا 17:0",
    "Comments": "",
    "MessageOnSignup": "«از دروس الزامی دورۀ ارشد»، ویژه دانشجویان ارشد ورودی 1402 گروه",
    "CourseID": ""
  },
  {
    "Group": "1",
    "Credits": "0",
    "Name": "پایان‌نامه کارشناسی‌ارشد",
    "Prereqs": "",
    "Capacity": "",
    "EnrolledStudents": "11",
    "Professor": "",
    "ExamDate": "",
    "ClassTime": "",
    "Comments": "",
    "MessageOnSignup": "",
    "CourseID": "بار اول به میزان 4 واحد و دفعات بعد به میزان 0 واحد ثبت و اخذ\n              کنید."
  },
  {
    "Group": "1",
    "Credits": "3",
    "Name": "تاریخ علم تمدن اسلامی",
    "Prereqs": "",
    "Capacity": "20",
    "EnrolledStudents": "8",
    "Professor": "بنفشه افتخاری",
    "ExamDate": "",
    "ClassTime": "شنبه از 13:0 تا 16:0",
    "Comments": "",
    "MessageOnSignup": "«درس جبرانی (الزامی در ترم اول دانشجو) برای دانشجویان دکتری ورودی\n              1402گروه» - کلیه دانشجویان گروه و دانشگاهحداکثر ظرفیت برای ورودی\n              های 1402 مقطع کارشناسی ارشد دانشکده گروه فلسفه علم 0 می باشد.",
    "CourseID": ""
  },
  {
    "Group": "1",
    "Credits": "3",
    "Name": "صلح، علم و فناوری",
    "Prereqs": "",
    "Capacity": "20",
    "EnrolledStudents": "20",
    "Professor": "یحیی صباغچی فیروز آباد",
    "ExamDate": "",
    "ClassTime": "دوشنبه از 9:0 تا 12:0",
    "Comments": "",
    "MessageOnSignup": "«از دروس اختیاری» - کلیه دانشجویان گروه و دانشگاهحداکثر ظرفیت برای\n              مقطع دکتری دانشکده گروه فلسفه علم 0 می باشد.\n              \n              حداکثر ظرفیت برای ورودی های 1402 مقطع کارشناسی ارشد دانشکده گروه\n              فلسفه علم 0 می باشد.",
    "CourseID": ""
  },
  {
    "Group": "1",
    "Credits": "3",
    "Name": "فلسفه روان‌کاوی",
    "Prereqs": "",
    "Capacity": "25",
    "EnrolledStudents": "25",
    "Professor": "محمدحسن مرصعی",
    "ExamDate": "",
    "ClassTime": "یکشنبه از 14:0 تا 17:0",
    "Comments": "",
    "MessageOnSignup": "«از دروس اختیاری» - کلیه دانشجویان گروه و دانشگاهحداکثر ظرفیت برای\n              مقطع دکتری دانشکده گروه فلسفه علم 0 می باشد.\n              \n              حداکثر ظرفیت برای ورودی های 1402 مقطع کارشناسی ارشد دانشکده گروه\n              فلسفه علم 0 می باشد.",
    "CourseID": ""
  },
  {
    "Group": "1",
    "Credits": "3",
    "Name": "مقدمه‌ای بر فلسفه علم",
    "Prereqs": "",
    "Capacity": "80",
    "EnrolledStudents": "25",
    "Professor": "مصطفی تقوی",
    "ExamDate": "",
    "ClassTime": "چهارشنبه از 10:0 تا 13:0",
    "Comments": "",
    "MessageOnSignup": "«از دروس الزامی دوره فرعی فلسفه علم» - کلیه دانشجویان دانشگاه (به\n              استثنای دانشجویان دوره های اصلی گروه)حداکثر ظرفیت برای ورودی های\n              1402 مقطع کارشناسی ارشد دانشکده گروه فلسفه علم 0 می باشد.",
    "CourseID": ""
  },
  {
    "Group": "1",
    "Credits": "0",
    "Name": "امتحان جامع دکتری",
    "Prereqs": "",
    "Capacity": "",
    "EnrolledStudents": "",
    "Professor": "",
    "ExamDate": "",
    "ClassTime": "",
    "Comments": "",
    "MessageOnSignup": "",
    "CourseID": ""
  },
  {
    "Group": "1",
    "Credits": "0",
    "Name": "پیشنهاد پژوهشی",
    "Prereqs": "",
    "Capacity": "",
    "EnrolledStudents": "",
    "Professor": "",
    "ExamDate": "",
    "ClassTime": "",
    "Comments": "",
    "MessageOnSignup": "",
    "CourseID": ""
  },
  {
    "Group": "1",
    "Credits": "2",
    "Name": "فلسفه علم پیشرفته ۱",
    "Prereqs": "",
    "Capacity": "7",
    "EnrolledStudents": "4",
    "Professor": "مصطفی تقوی",
    "ExamDate": "",
    "ClassTime": "شنبه از 16:0 تا 18:0",
    "Comments": "",
    "MessageOnSignup": "«از دروس الزامی دورۀ دکتری گروه»، ویژه دانشجویان دکتری ورودی 1402\n              گروهحداکثر ظرفیت برای مقطع کارشناسی ارشد 0 می باشد.\n              \n              حداکثر ظرفیت برای مقطع کارشناسی 0 می باشد.",
    "CourseID": ""
  },
  {
    "Group": "1",
    "Credits": "2",
    "Name": "فلسفه غرب پیشرفته",
    "Prereqs": "",
    "Capacity": "7",
    "EnrolledStudents": "5",
    "Professor": "سید علی طاهری خرم آبادی",
    "ExamDate": "",
    "ClassTime": "دوشنبه از 13:30 تا 15:30",
    "Comments": "",
    "MessageOnSignup": "«از دروس الزامی دورۀ دکتری گروه»، ویژه دانشجویان دکتری ورودی 1402\n              گروهحداکثر ظرفیت برای مقطع کارشناسی ارشد 1 می باشد.\n              \n              حداکثر ظرفیت برای مقطع کارشناسی 0 می باشد.",
    "CourseID": ""
  },
  {
    "Group": "1",
    "Credits": "2",
    "Name": "فلسفه اسلامی پیشرفته ۱",
    "Prereqs": "",
    "Capacity": "7",
    "EnrolledStudents": "4",
    "Professor": "سیدحسن حسینی سروری",
    "ExamDate": "",
    "ClassTime": "دوشنبه از 10:0 تا 12:0",
    "Comments": "",
    "MessageOnSignup": "«از دروس الزامی دورۀ دکتری گروه»، ویژه دانشجویان دکتری ورودی 1402\n              گروهحداکثر ظرفیت برای مقطع کارشناسی ارشد 0 می باشد.\n              \n              حداکثر ظرفیت برای مقطع کارشناسی 0 می باشد.",
    "CourseID": ""
  },
  {
    "Group": "1",
    "Credits": "0",
    "Name": "رساله دکتری",
    "Prereqs": "",
    "Capacity": "",
    "EnrolledStudents": "3",
    "Professor": "",
    "ExamDate": "",
    "ClassTime": "",
    "Comments": "",
    "MessageOnSignup": "",
    "CourseID": "ورودی های 96 و ماقبل تا چهار بار 5 واحدی و بعد از آن 0 واحدی ثبت و\n              اخذ نمایند. ورودی های 98 و به بعد سه بار 5 واحدی، یک بار 3 واحدی و\n              بعد از آن 0 واحدی ثبت و اخذ نمایند (مجموع واحدهای رساله برای ورودی\n              های 98 و به بعد 18 واحد می باشد)"
  },
  {
    "Group": "1",
    "Credits": "0",
    "Name": "دفاع از رساله دکتری",
    "Prereqs": "",
    "Capacity": "",
    "EnrolledStudents": "",
    "Professor": "",
    "ExamDate": "",
    "ClassTime": "",
    "Comments": "",
    "MessageOnSignup": "دانشجویان دکتری ورودی 95 و به بعد می بایست در ترمی که قصد دفاع از\n              رسالۀ خویش را دارند در این درس ثبت نام نموده باشند",
    "CourseID": "ویژۀ دانشجویان دکتری ورودی 95 و به بعد که قصد دفاع در این ترم را\n              دارند"
  },
  {
    "Group": "1",
    "Credits": "3",
    "Name": "دستیار آموزشی",
    "Prereqs": "همنیاز: 33715",
    "Capacity": "",
    "EnrolledStudents": "",
    "Professor": "",
    "ExamDate": "",
    "ClassTime": "",
    "Comments": "",
    "MessageOnSignup": "اخذ دو بار در طول دوره برای دانشجویان دکتری گروه الزامی است.حداکثر\n              ظرفیت برای مقطع دکتری دانشکده گروه فلسفه علم 0 می باشد.",
    "CourseID": ""
  }
]
